module/__init__.py
module/__main__.py
module/ascc.py
asciiani-0.3.dist-info/METADATA
asciiani-0.3.dist-info/WHEEL
asciiani-0.3.dist-info/top_level.txt
asciiani-0.3.dist-info/RECORD
