Metadata-Version: 2.1
Name: asciiani
Version: 0.3
Requires-Dist: windows-curses
Requires-Dist: moviepy
Requires-Dist: Pillow
